{
  "/[locale]/about/page": "app/[locale]/about/page.js",
  "/[locale]/blog/[slug]/page": "app/[locale]/blog/[slug]/page.js",
  "/[locale]/blog/page": "app/[locale]/blog/page.js",
  "/[locale]/book/[slug]/page": "app/[locale]/book/[slug]/page.js",
  "/[locale]/booking/[id]/page": "app/[locale]/booking/[id]/page.js",
  "/[locale]/booking/new/page": "app/[locale]/booking/new/page.js",
  "/[locale]/contact/page": "app/[locale]/contact/page.js",
  "/[locale]/cookies/page": "app/[locale]/cookies/page.js",
  "/[locale]/entrance-fee/page": "app/[locale]/entrance-fee/page.js",
  "/[locale]/faq/page": "app/[locale]/faq/page.js",
  "/[locale]/history/page": "app/[locale]/history/page.js",
  "/[locale]/location/page": "app/[locale]/location/page.js",
  "/[locale]/opening-hours/page": "app/[locale]/opening-hours/page.js",
  "/[locale]/page": "app/[locale]/page.js",
  "/[locale]/privacy/page": "app/[locale]/privacy/page.js",
  "/[locale]/refund-policy/page": "app/[locale]/refund-policy/page.js",
  "/[locale]/safety-guide/page": "app/[locale]/safety-guide/page.js",
  "/[locale]/safety/page": "app/[locale]/safety/page.js",
  "/[locale]/terms/page": "app/[locale]/terms/page.js",
  "/[locale]/tickets/combo-saadian-tombs/page": "app/[locale]/tickets/combo-saadian-tombs/page.js",
  "/[locale]/tickets/guided-tour/page": "app/[locale]/tickets/guided-tour/page.js",
  "/[locale]/tickets/page": "app/[locale]/tickets/page.js",
  "/[locale]/tickets/private-tour/page": "app/[locale]/tickets/private-tour/page.js",
  "/[locale]/tickets/skip-the-line/page": "app/[locale]/tickets/skip-the-line/page.js",
  "/_global-error/page": "app/_global-error/page.js",
  "/_not-found/page": "app/_not-found/page.js",
  "/admin/blog/[id]/page": "app/admin/blog/[id]/page.js",
  "/admin/blog/new/page": "app/admin/blog/new/page.js",
  "/admin/blog/page": "app/admin/blog/page.js",
  "/admin/bookings/[id]/page": "app/admin/bookings/[id]/page.js",
  "/admin/bookings/page": "app/admin/bookings/page.js",
  "/admin/login/page": "app/admin/login/page.js",
  "/admin/page": "app/admin/page.js",
  "/admin/reviews/[id]/page": "app/admin/reviews/[id]/page.js",
  "/admin/reviews/new/page": "app/admin/reviews/new/page.js",
  "/admin/reviews/page": "app/admin/reviews/page.js",
  "/admin/safety/[id]/page": "app/admin/safety/[id]/page.js",
  "/admin/safety/new/page": "app/admin/safety/new/page.js",
  "/admin/safety/page": "app/admin/safety/page.js",
  "/admin/settings/page": "app/admin/settings/page.js",
  "/admin/tickets/[slug]/page": "app/admin/tickets/[slug]/page.js",
  "/admin/tickets/page": "app/admin/tickets/page.js",
  "/api/admin/blog/[id]/route": "app/api/admin/blog/[id]/route.js",
  "/api/admin/blog/route": "app/api/admin/blog/route.js",
  "/api/admin/bookings/[id]/cancel/route": "app/api/admin/bookings/[id]/cancel/route.js",
  "/api/admin/bookings/[id]/resend/route": "app/api/admin/bookings/[id]/resend/route.js",
  "/api/admin/login/route": "app/api/admin/login/route.js",
  "/api/admin/logout/route": "app/api/admin/logout/route.js",
  "/api/admin/reviews/[id]/route": "app/api/admin/reviews/[id]/route.js",
  "/api/admin/reviews/route": "app/api/admin/reviews/route.js",
  "/api/admin/safety/[id]/route": "app/api/admin/safety/[id]/route.js",
  "/api/admin/safety/route": "app/api/admin/safety/route.js",
  "/api/admin/settings/route": "app/api/admin/settings/route.js",
  "/api/admin/tickets/[slug]/route": "app/api/admin/tickets/[slug]/route.js",
  "/api/admin/tickets/route": "app/api/admin/tickets/route.js",
  "/api/admin/upload/route": "app/api/admin/upload/route.js",
  "/api/bookings/route": "app/api/bookings/route.js",
  "/api/contact/route": "app/api/contact/route.js",
  "/api/track/event/route": "app/api/track/event/route.js",
  "/api/track/pageview/route": "app/api/track/pageview/route.js",
  "/favicon.ico/route": "app/favicon.ico/route.js",
  "/opengraph-image/route": "app-edge-has-no-entrypoint",
  "/page": "app/page.js",
  "/robots.txt/route": "app/robots.txt/route.js",
  "/sitemap.xml/route": "app/sitemap.xml/route.js",
  "/style-guide/page": "app/style-guide/page.js"
}